{"African-American & African": [ 
{"catalog_number": 2224, "subject_descr": "African-American & African", "subject": "AAS", "sessions": [{"meetings": [{"days": "MoTuWeThFr", "start_time": "10:00 AM", "end_time": "03:00 PM", "start_dt": "01/02/2023", "end_dt": "01/13/2023", "bldg_cd": "CAB", "bldg_has_coordinates": true, "facility_descr": "New Cabell Hall 332", "room": "332", "facility_id": "CAB 332", "instructor": "Lisa Shutt"}], "subject": "AAS", "section_type": "SEM", "instructors": [{"name": "Lisa Shutt", "email": "lt7q@virginia.edu"}], "topic": null, "enrollment_total": 11, "class_capacity": 15, "wait_tot": 0, "wait_cap": 10, "catalog_nbr": 2224, "class_section": 1, "descr": "Black Femininities and Masculinities in the US Media", "units": "3", "display_order": 2}], "descr": "Black Femininities and Masculinities in the US Media", "topic": null, "units": "3"}] 
}